s3_path_wrangler/__init__.py
s3_path_wrangler/paths.py
s3_path_wrangler-0.5.0.dist-info/LICENSE
s3_path_wrangler-0.5.0.dist-info/WHEEL
s3_path_wrangler-0.5.0.dist-info/METADATA
s3_path_wrangler-0.5.0.dist-info/RECORD
