Metadata-Version: 2.1
Name: s3-path-wrangler
Version: 0.5.0
Summary: Provides S3 path manipulation, similar to PurePath in pathlib
Home-page: https://github.com/Barbora-Data-Science/s3-path-wrangler
License: Apache-2.0
Author: Saulius Beinorius
Author-email: saulius.beinorius@gmail.com
Maintainer: Saulius Beinorius
Maintainer-email: saulius.beinorius@gmail.com
Requires-Python: >=3.7,<4.0
Classifier: License :: OSI Approved :: Apache Software License
Classifier: Programming Language :: Python :: 3
Classifier: Programming Language :: Python :: 3.7
Classifier: Programming Language :: Python :: 3.8
Classifier: Programming Language :: Python :: 3.9
Classifier: Topic :: Software Development :: Libraries :: Python Modules
Project-URL: Repository, https://github.com/Barbora-Data-Science/s3-path-wrangler
